{
    "questions": {
        "Které z těchto možností není bezpečnostní kontrola emailu?": {
            "type": "ABC",
            "answers": [
                "Zkrontolování adresy odesílatele.",
                "Zkontrolování příloh emailu.",
                "Kontrola času odeslání"
            ],
            "correct": 3
        },
        "Na jakých stránkách můžete zkontrolovat zdali je příloha opravdu nebezpečná nebo ne ?": {
            "type": "ABC",
            "answers": [
                "seznam.cz",
                "virustotal.com",
                "amazon.de"
            ],
            "correct": 2
        },
        "Kdo dělá tuto práci(kontrolování souborů) za nás ?": {
            "type": "ABC",
            "answers": [
                "Operační systém",
                "Webový prohlížeč",
                "Antivirus"
            ],
            "correct": 3
        }
    }
}